{
    "ID": "TRD121",
    "Name": "Turkish Language I",
    "prerequisiteID": "",
    "lectureType": "MANDATORY",
    "quota": 50,
    "credit": 2,
    "term": "Fall",
    "termYear": "Freshman",
    "lectureSessions": [
        {
            "ID": "1",
            "lectureID": "TRD121",
            "instructorID": "150097",
            "sessionType": "Theorytical",
            "sessionHours": [
                [
                    0,
                    0,
                    0,
                    0,
                    0,
                    0,
                    0,
                    0,
                    0,
                    0
                ],
                [
                    0,
                    0,
                    0,
                    0,
                    0,
                    0,
                    0,
                    0,
                    0,
                    0
                ],
                [
                    0,
                    0,
                    0,
                    0,
                    0,
                    0,
                    0,
                    0,
                    0,
                    0
                ],
                [
                    0,
                    0,
                    0,
                    0,
                    0,
                    0,
                    0,
                    0,
                    0,
                    0
                ],
                [
                    0,
                    0,
                    0,
                    0,
                    0,
                    1,
                    1,
                    0,
                    0,
                    0
                ],
                [
                    0,
                    0,
                    0,
                    0,
                    0,
                    0,
                    0,
                    0,
                    0,
                    0
                ],
                [
                    0,
                    0,
                    0,
                    0,
                    0,
                    0,
                    0,
                    0,
                    0,
                    0
                ]
            ]
        }
    ]
}